{"ranking":[{"name":"Afghanistan","value":121415},{"name":"Albania","value":36879},{"name":"Algeria","value":117726},{"name":"Andorra","value":15419},{"name":"Angola","value":66982},{"name":"Argentina","value":177475},{"name":"Armenia","value":95242},{"name":"Australia","value":368942},{"name":"Austria","value":315409},{"name":"Azerbaijan","value":111299},{"name":"Bahrain","value":18649},{"name":"Bangladesh","value":229015},{"name":"Belarus","value":96850},{"name":"Belgium","value":312220},{"name":"Benin","value":61677},{"name":"Bhutan","value":11066},{"name":"Bolivia","value":64719},{"name":"Bosnia and Herz.","value":921},{"name":"Botswana","value":19060},{"name":"Brazil","value":240396},{"name":"Bulgaria","value":218554},{"name":"Burkina Faso","value":6385},{"name":"Burundi","value":14358},{"name":"Cambodia","value":57362},{"name":"Cameroon","value":139227},{"name":"Canada","value":395443},{"name":"Chad","value":5992},{"name":"Chile","value":138934},{"name":"China","value":342707},{"name":"Colombia","value":145572},{"name":"Congo","value":26129},{"name":"Croatia","value":144633},{"name":"Cuba","value":72460},{"name":"Cyprus","value":88628},{"name":"Czechia","value":315321},{"name":"Denmark","value":268279},{"name":"Dominican Rep.","value":36738},{"name":"Ecuador","value":115218},{"name":"Egypt","value":256293},{"name":"El Salvador","value":51742},{"name":"Estonia","value":19523},{"name":"Ethiopia","value":334632},{"name":"Finland","value":266365},{"name":"France","value":536065},{"name":"Georgia","value":143404},{"name":"Germany","value":618361},{"name":"Ghana","value":284542},{"name":"Greece","value":153582},{"name":"Guatemala","value":78941},{"name":"Honduras","value":39225},{"name":"Hong Kong","value":191712},{"name":"Hungary","value":202589},{"name":"Iceland","value":57825},{"name":"India","value":285554},{"name":"Indonesia","value":344438},{"name":"Iran","value":252474},{"name":"Iraq","value":57616},{"name":"Ireland","value":171275},{"name":"Israel","value":228211},{"name":"Italy","value":359747},{"name":"Jamaica","value":54965},{"name":"Japan","value":505149},{"name":"Jordan","value":57107},{"name":"Kazakhstan","value":81760},{"name":"Kenya","value":435652},{"name":"Kuwait","value":16863},{"name":"Laos","value":6762},{"name":"Latvia","value":59549},{"name":"Lithuania","value":86422},{"name":"Luxembourg","value":62937},{"name":"Madagascar","value":106386},{"name":"Malawi","value":47672},{"name":"Malaysia","value":153271},{"name":"Maldives","value":9342},{"name":"Mali","value":14648},{"name":"Malta","value":40847},{"name":"Mauritania","value":4705},{"name":"Mauritius","value":30652},{"name":"Mexico","value":146157},{"name":"Moldova","value":51831},{"name":"Mongolia","value":36521},{"name":"Montenegro","value":53401},{"name":"Morocco","value":293291},{"name":"Mozambique","value":43926},{"name":"Myanmar","value":99046},{"name":"Namibia","value":15375},{"name":"Nepal","value":175204},{"name":"Netherlands","value":434448},{"name":"New Zealand","value":156219},{"name":"Nicaragua","value":99674},{"name":"Nigeria","value":259036},{"name":"Norway","value":288029},{"name":"Oman","value":19126},{"name":"Pakistan","value":198966},{"name":"Palestine","value":93148},{"name":"Panama","value":30403},{"name":"Paraguay","value":56501},{"name":"Peru","value":107424},{"name":"Philippines","value":309365},{"name":"Poland","value":356368},{"name":"Portugal","value":272077},{"name":"Qatar","value":20188},{"name":"Romania","value":181249},{"name":"Russia","value":239320},{"name":"Rwanda","value":245991},{"name":"San Marino","value":2004},{"name":"Saudi Arabia","value":41239},{"name":"Senegal","value":54324},{"name":"Serbia","value":157228},{"name":"Sierra Leone","value":6339},{"name":"Singapore","value":221515},{"name":"Slovakia","value":131844},{"name":"Slovenia","value":106768},{"name":"South Africa","value":149691},{"name":"South Korea","value":310178},{"name":"Spain","value":375992},{"name":"Sri Lanka","value":165905},{"name":"Sudan","value":45362},{"name":"Sweden","value":314479},{"name":"Switzerland","value":376073},{"name":"Syria","value":34813},{"name":"Taiwan","value":299306},{"name":"Tanzania","value":109889},{"name":"Thailand","value":204050},{"name":"Tunisia","value":116726},{"name":"Turkey","value":181763},{"name":"Uganda","value":193194},{"name":"Ukraine","value":237744},{"name":"United Arab Emirates","value":586},{"name":"United Kingdom","value":404755},{"name":"United States of America","value":408677},{"name":"Uruguay","value":116457},{"name":"Uzbekistan","value":163022},{"name":"Venezuela","value":121167},{"name":"Vietnam","value":203402},{"name":"Yemen","value":57513},{"name":"Zambia","value":51135},{"name":"Zambia","value":52534}]}
