{"ranking":[{"name":"Afghanistan","value":112240},{"name":"Albania","value":35663},{"name":"Algeria","value":124543},{"name":"Andorra","value":12728},{"name":"Angola","value":68397},{"name":"Argentina","value":184808},{"name":"Armenia","value":95873},{"name":"Australia","value":372039},{"name":"Austria","value":325298},{"name":"Azerbaijan","value":129324},{"name":"Bahrain","value":19775},{"name":"Bangladesh","value":214616},{"name":"Belarus","value":96335},{"name":"Belgium","value":311165},{"name":"Benin","value":58534},{"name":"Bhutan","value":11036},{"name":"Bolivia","value":64143},{"name":"Bosnia and Herz.","value":992},{"name":"Botswana","value":16308},{"name":"Brazil","value":231655},{"name":"Bulgaria","value":211386},{"name":"Burkina Faso","value":4487},{"name":"Burundi","value":13437},{"name":"Cambodia","value":62157},{"name":"Cameroon","value":129582},{"name":"Canada","value":388729},{"name":"Chad","value":6172},{"name":"Chile","value":139892},{"name":"China","value":329203},{"name":"Colombia","value":138388},{"name":"Congo","value":25900},{"name":"Croatia","value":140486},{"name":"Cuba","value":89258},{"name":"Cyprus","value":93001},{"name":"Czechia","value":310055},{"name":"Denmark","value":265117},{"name":"Dominican Rep.","value":38371},{"name":"Ecuador","value":105181},{"name":"Egypt","value":233990},{"name":"El Salvador","value":52861},{"name":"Estonia","value":112707},{"name":"Ethiopia","value":315075},{"name":"Finland","value":257501},{"name":"France","value":540737},{"name":"Georgia","value":148179},{"name":"Germany","value":606901},{"name":"Ghana","value":252016},{"name":"Greece","value":152701},{"name":"Guatemala","value":76307},{"name":"Honduras","value":39046},{"name":"Hong Kong","value":178439},{"name":"Hungary","value":206149},{"name":"Iceland","value":58047},{"name":"India","value":279368},{"name":"Indonesia","value":349976},{"name":"Iran","value":253347},{"name":"Iraq","value":59287},{"name":"Ireland","value":173668},{"name":"Israel","value":218987},{"name":"Italy","value":367079},{"name":"Jamaica","value":56941},{"name":"Japan","value":498953},{"name":"Jordan","value":52666},{"name":"Kazakhstan","value":79144},{"name":"Kenya","value":394428},{"name":"Kuwait","value":16959},{"name":"Laos","value":6597},{"name":"Latvia","value":60018},{"name":"Lithuania","value":86177},{"name":"Luxembourg","value":61531},{"name":"Madagascar","value":105509},{"name":"Malawi","value":41462},{"name":"Malaysia","value":156231},{"name":"Maldives","value":9339},{"name":"Mali","value":14031},{"name":"Malta","value":37166},{"name":"Mauritania","value":5021},{"name":"Mauritius","value":28754},{"name":"Mexico","value":153009},{"name":"Moldova","value":46079},{"name":"Mongolia","value":36078},{"name":"Montenegro","value":50221},{"name":"Morocco","value":279453},{"name":"Mozambique","value":37249},{"name":"Myanmar","value":95591},{"name":"Namibia","value":14412},{"name":"Nepal","value":170330},{"name":"Netherlands","value":437001},{"name":"New Zealand","value":162321},{"name":"Nicaragua","value":102738},{"name":"Nigeria","value":233063},{"name":"Norway","value":278690},{"name":"Oman","value":17729},{"name":"Pakistan","value":185295},{"name":"Palestine","value":86391},{"name":"Panama","value":31118},{"name":"Paraguay","value":56540},{"name":"Peru","value":101155},{"name":"Philippines","value":312022},{"name":"Poland","value":352435},{"name":"Portugal","value":259572},{"name":"Qatar","value":19975},{"name":"Romania","value":180369},{"name":"Russia","value":246032},{"name":"Rwanda","value":231503},{"name":"San Marino","value":2280},{"name":"Saudi Arabia","value":39597},{"name":"Senegal","value":52010},{"name":"Serbia","value":152849},{"name":"Sierra Leone","value":6274},{"name":"Singapore","value":218301},{"name":"Slovakia","value":125565},{"name":"Slovenia","value":112983},{"name":"South Africa","value":147471},{"name":"South Korea","value":319883},{"name":"Spain","value":378303},{"name":"Sri Lanka","value":171123},{"name":"Sudan","value":38644},{"name":"Sweden","value":311191},{"name":"Switzerland","value":389745},{"name":"Syria","value":35837},{"name":"Taiwan","value":296973},{"name":"Tanzania","value":99207},{"name":"Thailand","value":201580},{"name":"Tunisia","value":117623},{"name":"Turkey","value":176805},{"name":"Uganda","value":169249},{"name":"Ukraine","value":220510},{"name":"United Arab Emirates","value":334},{"name":"United Kingdom","value":403877},{"name":"United States of America","value":400495},{"name":"Uruguay","value":115544},{"name":"Uzbekistan","value":152350},{"name":"Venezuela","value":120693},{"name":"Vietnam","value":205654},{"name":"Yemen","value":61553},{"name":"Zambia","value":48881},{"name":"Zambia","value":49383}]}
